{
  "created_at_utc": "20260719T100627Z",
  "benchmark": "pg19_ppl_context_sweep",
  "model_id": "meta-llama/Llama-3.1-8B",
  "context_plan": [
    [
      32768,
      4
    ],
    [
      65536,
      2
    ]
  ],
  "generate_tokens": 256,
  "methods": [
    "full_attention",
    "quest_p16_b4096",
    "fier_triton_g32_b4096",
    "bit2_cuda_popc_g32_b4096",
    "quest_p16_b8192",
    "fier_triton_g32_b8192",
    "bit2_cuda_popc_g32_b8192"
  ],
  "budget_sweep": [
    4096,
    8192
  ],
  "group_size": 32,
  "quest_page_size": 16,
  "fier_backend": "triton",
  "full_layers": [
    0,
    1
  ],
  "measure_topk_recall_vs_exact_qk_topk": false,
  "dataset_name": "deepmind/pg19",
  "dataset_split": "test",
  "pg19_loader": "partial",
  "pg19_max_books": 64,
  "dtype": "float16",
  "attention": "sdpa",
  "device_map": "cuda:0",
  "expected_runtime_note": "Default plan is intended to finish within roughly 3 hours on one RTX A6000, excluding first-time model download."
}
