[
  {
    "method": "bit2_qk_cuda_popc_g32_b4096",
    "num_tokens": 384,
    "mean_nll": 2.460287357839699,
    "perplexity": 11.708175492645003,
    "mean_candidate_ratio": 0.12475839324736661,
    "mean_prepack_ms": 0.0,
    "mean_decode_ms_per_token": 622.5242262395719,
    "mean_candidate_search_ms_per_token": 31.478593176166516,
    "mean_cache_update_ms_per_token": 14.567184029147029,
    "mean_selected_attention_ms_per_token": 157.1269100806288,
    "mean_candidate_search_ops_proxy": 30920130720.0,
    "mean_topk_recall": null
  },
  {
    "method": "bit2_qk_cuda_popc_g32_b8192",
    "num_tokens": 384,
    "mean_nll": 2.360692246123382,
    "perplexity": 10.59828553572214,
    "mean_candidate_ratio": 0.24951678649473322,
    "mean_prepack_ms": 0.0,
    "mean_decode_ms_per_token": 657.9013651159281,
    "mean_candidate_search_ms_per_token": 31.617375573120928,
    "mean_cache_update_ms_per_token": 14.574553196628889,
    "mean_selected_attention_ms_per_token": 159.26099466511127,
    "mean_candidate_search_ops_proxy": 30951648960.0,
    "mean_topk_recall": null
  },
  {
    "method": "bit2_qk_group_mean2_g32_b4096",
    "num_tokens": 384,
    "mean_nll": 2.323000592399475,
    "perplexity": 10.206253211528086,
    "mean_candidate_ratio": 0.12475839324736661,
    "mean_prepack_ms": 0.0,
    "mean_decode_ms_per_token": 883.2310703777088,
    "mean_candidate_search_ms_per_token": 296.51385325631117,
    "mean_cache_update_ms_per_token": 14.56457893558157,
    "mean_selected_attention_ms_per_token": 156.51635739936805,
    "mean_candidate_search_ops_proxy": 30920130720.0,
    "mean_topk_recall": null
  },
  {
    "method": "bit2_qk_group_mean2_g32_b8192",
    "num_tokens": 384,
    "mean_nll": 2.3222536050142355,
    "perplexity": 10.198632115914029,
    "mean_candidate_ratio": 0.24951678649473322,
    "mean_prepack_ms": 0.0,
    "mean_decode_ms_per_token": 916.9089179486036,
    "mean_candidate_search_ms_per_token": 296.3582935049556,
    "mean_cache_update_ms_per_token": 14.56942223982575,
    "mean_selected_attention_ms_per_token": 157.82857440629354,
    "mean_candidate_search_ops_proxy": 30951648960.0,
    "mean_topk_recall": null
  },
  {
    "method": "bit2_qk_group_mean4_g32_b4096",
    "num_tokens": 384,
    "mean_nll": 2.323351574086832,
    "perplexity": 10.209836048220112,
    "mean_candidate_ratio": 0.12475839324736661,
    "mean_prepack_ms": 0.0,
    "mean_decode_ms_per_token": 1115.549252834171,
    "mean_candidate_search_ms_per_token": 529.5455527442913,
    "mean_cache_update_ms_per_token": 14.579178551988056,
    "mean_selected_attention_ms_per_token": 156.1821949078973,
    "mean_candidate_search_ops_proxy": 30920130720.0,
    "mean_topk_recall": null
  },
  {
    "method": "bit2_qk_group_mean4_g32_b8192",
    "num_tokens": 384,
    "mean_nll": 2.3222081799773666,
    "perplexity": 10.198168853196094,
    "mean_candidate_ratio": 0.24951678649473322,
    "mean_prepack_ms": 0.0,
    "mean_decode_ms_per_token": 1151.855633458278,
    "mean_candidate_search_ms_per_token": 529.5334047841874,
    "mean_cache_update_ms_per_token": 14.586793268487478,
    "mean_selected_attention_ms_per_token": 158.30275367757227,
    "mean_candidate_search_ops_proxy": 30951648960.0,
    "mean_topk_recall": null
  },
  {
    "method": "fier_triton_g32_b4096",
    "num_tokens": 384,
    "mean_nll": 2.326157787520399,
    "perplexity": 10.238527265304334,
    "mean_candidate_ratio": 0.12475839324736661,
    "mean_prepack_ms": 0.0,
    "mean_decode_ms_per_token": 647.3724995739758,
    "mean_candidate_search_ms_per_token": 62.166992963937446,
    "mean_cache_update_ms_per_token": 14.562041770356396,
    "mean_selected_attention_ms_per_token": 156.37772555831665,
    "mean_candidate_search_ops_proxy": 24584227200.0,
    "mean_topk_recall": null
  },
  {
    "method": "fier_triton_g32_b8192",
    "num_tokens": 384,
    "mean_nll": 2.32217394443903,
    "perplexity": 10.197819719371783,
    "mean_candidate_ratio": 0.24951678649473322,
    "mean_prepack_ms": 0.0,
    "mean_decode_ms_per_token": 681.6714557353407,
    "mean_candidate_search_ms_per_token": 62.1018862738371,
    "mean_cache_update_ms_per_token": 14.577779453247786,
    "mean_selected_attention_ms_per_token": 158.3900562758014,
    "mean_candidate_search_ops_proxy": 24615745440.0,
    "mean_topk_recall": null
  }
]
